{
	"id": "BptEIOqTJwY6VQf",
	"json": "{\"id\":\"BptEIOqTJwY6VQf\",\"url\":\"https://ise.illinois.edu/directory/faculty/awards\",\"loadedUrl\":\"https://ise.illinois.edu/directory/faculty/awards\",\"uniqueKey\":\"https://ise.illinois.edu/directory/faculty/awards\",\"method\":\"GET\",\"noRetry\":false,\"retryCount\":0,\"errorMessages\":[],\"headers\":{},\"userData\":{\"__crawlee\":{\"state\":4}},\"handledAt\":\"2026-06-16T21:48:40.409Z\"}",
	"method": "GET",
	"orderNo": null,
	"retryCount": 0,
	"uniqueKey": "https://ise.illinois.edu/directory/faculty/awards",
	"url": "https://ise.illinois.edu/directory/faculty/awards"
}