{
	"id": "SkerQ71K80b2SEu",
	"json": "{\"id\":\"SkerQ71K80b2SEu\",\"url\":\"https://grainger.illinois.edu/calendars\",\"loadedUrl\":\"https://grainger.illinois.edu/calendars\",\"uniqueKey\":\"https://grainger.illinois.edu/calendars\",\"method\":\"GET\",\"noRetry\":false,\"retryCount\":0,\"errorMessages\":[],\"headers\":{},\"userData\":{\"__crawlee\":{\"crawlDepth\":1,\"enqueueStrategy\":\"all\",\"state\":4}},\"handledAt\":\"2026-06-15T23:14:07.409Z\"}",
	"method": "GET",
	"orderNo": null,
	"retryCount": 0,
	"uniqueKey": "https://grainger.illinois.edu/calendars",
	"url": "https://grainger.illinois.edu/calendars"
}