{
	"id": "vbYYajx2rQLn1vo",
	"json": "{\"id\":\"vbYYajx2rQLn1vo\",\"url\":\"https://energysystemsmeng.engineering.illinois.edu/\",\"loadedUrl\":\"https://energysystemsmeng.grainger.illinois.edu/\",\"uniqueKey\":\"https://energysystemsmeng.engineering.illinois.edu\",\"method\":\"GET\",\"noRetry\":false,\"retryCount\":0,\"errorMessages\":[],\"headers\":{},\"userData\":{\"__crawlee\":{\"crawlDepth\":2,\"enqueueStrategy\":\"all\",\"state\":4}},\"handledAt\":\"2026-06-16T21:46:46.419Z\"}",
	"method": "GET",
	"orderNo": null,
	"retryCount": 0,
	"uniqueKey": "https://energysystemsmeng.engineering.illinois.edu",
	"url": "https://energysystemsmeng.engineering.illinois.edu/"
}