{
	"id": "WWCyVVOnW7O2SKz",
	"json": "{\"id\":\"WWCyVVOnW7O2SKz\",\"url\":\"https://my.engr.illinois.edu/elections/\",\"loadedUrl\":\"https://my.engr.illinois.edu/login.asp?/elections/index.asp\",\"uniqueKey\":\"https://my.engr.illinois.edu/elections\",\"method\":\"GET\",\"noRetry\":false,\"retryCount\":0,\"errorMessages\":[],\"headers\":{},\"userData\":{\"__crawlee\":{\"crawlDepth\":2,\"state\":4}},\"handledAt\":\"2026-06-16T21:50:23.371Z\"}",
	"method": "GET",
	"orderNo": null,
	"retryCount": 0,
	"uniqueKey": "https://my.engr.illinois.edu/elections",
	"url": "https://my.engr.illinois.edu/elections/"
}