{
	"id": "YdJ4m2Y1J4SWrSs",
	"json": "{\"id\":\"YdJ4m2Y1J4SWrSs\",\"url\":\"https://ise.illinois.edu/directory/profile/jrehg\",\"loadedUrl\":\"https://ise.illinois.edu/directory/profile/jrehg\",\"uniqueKey\":\"https://ise.illinois.edu/directory/profile/jrehg\",\"method\":\"GET\",\"noRetry\":false,\"retryCount\":0,\"errorMessages\":[],\"headers\":{},\"userData\":{\"__crawlee\":{\"crawlDepth\":1,\"state\":4}},\"handledAt\":\"2026-06-16T21:49:54.656Z\"}",
	"method": "GET",
	"orderNo": null,
	"retryCount": 0,
	"uniqueKey": "https://ise.illinois.edu/directory/profile/jrehg",
	"url": "https://ise.illinois.edu/directory/profile/jrehg"
}