{
	"id": "YjpG73SkFTTYLSC",
	"json": "{\"id\":\"YjpG73SkFTTYLSC\",\"url\":\"https://bioengineering.illinois.edu/academics/graduate/ms\",\"loadedUrl\":\"https://bioengineering.illinois.edu/academics/graduate/ms\",\"uniqueKey\":\"https://bioengineering.illinois.edu/academics/graduate/ms\",\"method\":\"GET\",\"noRetry\":false,\"retryCount\":0,\"errorMessages\":[],\"headers\":{},\"userData\":{\"__crawlee\":{\"crawlDepth\":2,\"enqueueStrategy\":\"all\",\"state\":4}},\"handledAt\":\"2026-06-16T21:46:50.621Z\"}",
	"method": "GET",
	"orderNo": null,
	"retryCount": 0,
	"uniqueKey": "https://bioengineering.illinois.edu/academics/graduate/ms",
	"url": "https://bioengineering.illinois.edu/academics/graduate/ms"
}