{
	"id": "ZRRKApS0X0vFC4N",
	"json": "{\"id\":\"ZRRKApS0X0vFC4N\",\"url\":\"https://ise.illinois.edu/directory/profile/beck3\",\"loadedUrl\":\"https://ise.illinois.edu/directory/profile/beck3\",\"uniqueKey\":\"https://ise.illinois.edu/directory/profile/beck3\",\"method\":\"GET\",\"noRetry\":false,\"retryCount\":0,\"errorMessages\":[],\"headers\":{},\"userData\":{\"__crawlee\":{\"crawlDepth\":1,\"state\":4}},\"handledAt\":\"2026-06-16T21:49:30.370Z\"}",
	"method": "GET",
	"orderNo": null,
	"retryCount": 0,
	"uniqueKey": "https://ise.illinois.edu/directory/profile/beck3",
	"url": "https://ise.illinois.edu/directory/profile/beck3"
}